README.rst
setup.py
src/cuisine_sweet/__init__.py
src/cuisine_sweet/git.py
src/cuisine_sweet/utils.py
src/cuisine_sweet/version.py
src/cuisine_sweet.egg-info/PKG-INFO
src/cuisine_sweet.egg-info/SOURCES.txt
src/cuisine_sweet.egg-info/dependency_links.txt
src/cuisine_sweet.egg-info/requires.txt
src/cuisine_sweet.egg-info/top_level.txt
src/cuisine_sweet/ensure/__init__.py
src/cuisine_sweet/ensure/cpan_module.py
src/cuisine_sweet/ensure/fs.py
src/cuisine_sweet/ensure/git.py
src/cuisine_sweet/ensure/local_git.py
src/cuisine_sweet/ensure/supervisord.py
src/cuisine_sweet/ensure/user_crontab.py
src/cuisine_sweet/ensure/yum.py