Metadata-Version: 1.1
Name: cuisine-sweet
Version: 0.1.17
Summary: Sugar-coated declarative deployment recipes built on top of Fabric and Cuisine
Home-page: http://github.com/dexterbt1/cuisine_sweet
Author: Dexter Tad-y
Author-email: dtady@cpan.org
License: Revised BSD License
Download-URL: https://github.com/dexterbt1/cuisine_sweet/tarball/0.1.17
Keywords: fabric,cuisine,deployment
Platform: UNKNOWN
Classifier: Programming Language :: Python
Classifier: Development Status :: 3 - Alpha
Classifier: Natural Language :: English
Classifier: Environment :: Web Environment
Classifier: Intended Audience :: Developers
Classifier: Operating System :: OS Independent
Classifier: Topic :: Utilities
